PrintiPy_New/__init__.py
PrintiPy_New/PrintiPy_New.py
printipy_new-0.0.1.dist-info/LICENSE
printipy_new-0.0.1.dist-info/METADATA
printipy_new-0.0.1.dist-info/WHEEL
printipy_new-0.0.1.dist-info/RECORD
