Metadata-Version: 2.1
Name: printipy-new
Version: 0.0.1
Summary: PrintiPy is a wrapper for the rest API of Printify
Author: Dario Bräuning
Requires-Python: >=3.10,<4.0
Classifier: Development Status :: 2 - Pre-Alpha
Classifier: Operating System :: MacOS :: MacOS X
Classifier: Operating System :: Microsoft :: Windows
Classifier: Operating System :: Unix
Classifier: Programming Language :: Python :: 3
Classifier: Programming Language :: Python :: 3.10
Classifier: Programming Language :: Python :: 3.11
Requires-Dist: opencv-python (>=4.8.0.74,<5.0.0.0)
Requires-Dist: requests (>=2.31.0,<3.0.0)
